nocmd/__init__.py
nocmd/__version__.py
nocmd/plugin.py
nocmd-2024.12.25.dist-info/METADATA
nocmd-2024.12.25.dist-info/WHEEL
nocmd-2024.12.25.dist-info/entry_points.txt
nocmd-2024.12.25.dist-info/licenses/LICENSE
nocmd-2024.12.25.dist-info/RECORD
